[
    {
        "split": 0,
        "mse": 2928.622534298934,
        "rmse": 54.11674911059361
    },
    {
        "split": 1,
        "mse": 1616.9203614984565,
        "rmse": 40.21094827902541
    },
    {
        "split": 2,
        "mse": 610.0360167953623,
        "rmse": 24.698907198403784
    },
    {
        "split": 3,
        "mse": 286.2460190788836,
        "rmse": 16.918806668287324
    },
    {
        "split": 4,
        "mse": 232.8114687205322,
        "rmse": 15.258160725347343
    },
    {
        "mse": 1134.9272800784338,
        "rmse": 30.240714396331498
    }
]